{
  "name": "Gãy thân xương đùi_MCQ",
  "description": "Bộ đề ôn thi nội trú về gãy thân xương đùi - 50 câu MCQ bao gồm kiến thức về giải phẫu, cơ chế chấn thương, chẩn đoán và điều trị",
  "level": "ôn thi nội trú",
  "type": "mcq",
  "category": "Ngoại",
  "subcategory": "Chấn thương Chỉnh hình",
  "questions": [
    {
      "q": "Vị trí giải phẫu của gãy thân xương đùi được giới hạn ở đoạn nào?",
      "options": [
        "Dưới mấu chuyển nhỏ 2 cm đến trên lồi cầu 2 cm",
        "Dưới mấu chuyển nhỏ 5 cm đến trên lồi cầu 5 cm",
        "Dưới mấu chuyển lớn 5 cm đến trên lồi cầu 2 cm",
        "Dưới cổ xương đùi đến ranh giới sụn khớp lồi cầu"
      ],
      "answer": 1,
      "explain": "Đây là định nghĩa kinh điển về giới hạn thân xương đùi trong chấn thương chỉnh hình. Đoạn này có cấu trúc xương ống đặc, chịu lực uốn bẻ rất lớn."
    },
    {
      "q": "Đặc điểm nào sau đây KHÔNG đúng khi nói về gãy thân xương đùi ở người trưởng thành?",
      "options": [
        "Thường do lực chấn thương rất mạnh",
        "Có nguy cơ sốc chấn thương rất cao",
        "Đa số được điều trị ưu tiên bằng phương pháp bảo tồn",
        "Thường đi kèm các tổn thương đa chấn thương khác"
      ],
      "answer": 2,
      "explain": "Ở người trưởng thành, gãy thân xương đùi ưu tiên điều trị phẫu thuật (đóng đinh nội tủy) sớm để vận động nhanh, tránh các biến chứng nằm lâu. Điều trị bảo tồn chủ yếu dành cho trẻ em."
    },
    {
      "q": "Lượng máu mất trung bình ra xung quanh ổ gãy trong gãy kín thân xương đùi ở người lớn ước tính khoảng bao nhiêu?",
      "options": [
        "200 - 500 ml",
        "500 - 1000 ml",
        "1000 - 1500 ml",
        "1500 - 2000 ml"
      ],
      "answer": 2,
      "explain": "Khối lượng cơ đùi rất lớn và nguồn cấp máu dồi dào khiến gãy xương đùi có thể mất tới 1 lít rưỡi máu, nguy cơ gây sốc giảm thể tích ngay cả khi gãy kín."
    },
    {
      "q": "Trong phân loại mức độ tổn thương phần mềm của Tscherne đối với gãy xương kín, gãy thân xương đùi có vùng đùi sưng nề mạnh, căng bóng, phỏng nước, hội chứng chèn ép khoang tương ứng với độ mấy?",
      "options": [
        "Độ 0",
        "Độ 1",
        "Độ 2",
        "Độ 3"
      ],
      "answer": 3,
      "explain": "Độ 3 theo Tscherne mô tả tổn thương dập nát phần mềm nghiêm trọng, bong lóc da, có thể kèm theo hội chứng chèn ép khoang hoặc chấn thương mạch máu."
    },
    {
      "q": "Đặc điểm giải phẫu nào của xương đùi khiến quá trình liền xương ở vị trí này thường thuận lợi và tạo can xù to?",
      "options": [
        "Nằm nông ngay dưới da giúp dễ nắn chỉnh",
        "Ống tủy rất hẹp và ít mạch máu tủy",
        "Được bao bọc bởi khối cơ đồ sộ và nguồn cấp máu phong phú",
        "Cấu trúc xương xốp chiếm đa số ở phần thân xương"
      ],
      "answer": 2,
      "explain": "Thân xương đùi có hệ thống cơ bao bọc dày đặc, máu nuôi từ màng xương dồi dào. Nhờ đó, nếu được bất động tốt, can xương tạo ra rất mạnh và nhanh."
    },
    {
      "q": "Nguyên nhân phổ biến nhất gây gãy thân xương đùi ở độ tuổi thanh niên là gì?",
      "options": [
        "Loãng xương sinh lý",
        "Tai nạn giao thông",
        "U xương nguyên phát",
        "Tai nạn sinh hoạt trượt ngã nhẹ"
      ],
      "answer": 1,
      "explain": "Do xương đùi rất chắc khỏe, để bẻ gãy thân xương đùi ở người trẻ cần một năng lượng cao, điển hình nhất là tai nạn giao thông hoặc ngã từ trên cao."
    },
    {
      "q": "Cơ chế chấn thương gián tiếp do lực vặn xoắn thường gây ra hình thái đường gãy nào ở thân xương đùi?",
      "options": [
        "Gãy ngang",
        "Gãy nát phần vỏ xương",
        "Gãy chéo xoắn",
        "Gãy phức tạp nhiều tầng"
      ],
      "answer": 2,
      "explain": "Lực uốn bẻ trực tiếp thường gây gãy ngang hoặc gãy mảnh rời (hình cánh bướm), trong khi lực vặn xoắn (bàn chân bị kẹt, người xoay) gây gãy chéo xoắn kinh điển."
    },
    {
      "q": "Trong gãy 1/3 trên thân xương đùi, đoạn gãy gần thường bị lệch theo tư thế nào do lực kéo của các cơ?",
      "options": [
        "Gập ra trước, dạng và xoay ngoài",
        "Khép, duỗi và xoay trong",
        "Gập ra sau, khép và xoay trong",
        "Duỗi, dạng và xoay ngoài"
      ],
      "answer": 0,
      "explain": "Đây là bẫy giải phẫu cơ bản: Cơ thắt lưng chậu kéo gập ra trước, các cơ mông kéo dạng, nhóm cơ xoay ngắn kéo xoay ngoài đoạn gãy gần."
    },
    {
      "q": "Yếu tố giải phẫu nào giải thích cho sự di lệch gập góc ra sau của đoạn gãy xa trong gãy 1/3 dưới xương đùi?",
      "options": [
        "Sự co kéo của cơ tứ đầu đùi",
        "Sự co kéo của cơ thắt lưng chậu",
        "Sự co kéo của cơ sinh đôi",
        "Sự co kéo của nhóm cơ khép"
      ],
      "answer": 2,
      "explain": "Cơ sinh đôi bám vào lồi cầu đùi, khi gãy 1/3 dưới, cơ này co rút sẽ kéo đầu nhọn của đoạn gãy xa chọc ra phía sau vào hố khoeo."
    },
    {
      "q": "Biến dạng gập góc mở vào trong (tạo hình chữ V mở vào trong) ở đùi sau gãy thân xương đùi chủ yếu do sự co kéo của nhóm cơ nào?",
      "options": [
        "Nhóm cơ mông",
        "Nhóm cơ khép",
        "Nhóm cơ tứ đầu đùi",
        "Nhóm cơ ngồi khoeo"
      ],
      "answer": 1,
      "explain": "Nhóm cơ khép bám dọc đường ráp xương đùi có xu hướng kéo đoạn gãy xa vào trong, tạo nên góc mở vào trong (hoặc góc lồi ra ngoài)."
    },
    {
      "q": "Nguồn cấp máu chính cho thân xương đùi chủ yếu xuất phát từ động mạch nào?",
      "options": [
        "Động mạch đùi nông",
        "Động mạch khoeo",
        "Động mạch bịt",
        "Động mạch đùi sâu"
      ],
      "answer": 3,
      "explain": "Các nhánh xiên của động mạch đùi sâu cung cấp máu chính cho thân xương đùi, đặc biệt là tủy xương và phần trong màng xương."
    },
    {
      "q": "Trong chấn thương gãy xương đùi, cơ chế bệnh sinh cốt lõi gây ra hội chứng tắc mạch mỡ là gì?",
      "options": [
        "Cục máu đông từ tĩnh mạch sâu bong ra đi lên phổi",
        "Áp lực nội tủy tăng cao đẩy hạt mỡ từ tủy xương tràn vào hệ tĩnh mạch",
        "Rối loạn đông máu tạo các vi huyết khối toàn thân",
        "Suy hô hấp cấp làm hoại tử mỡ dưới da"
      ],
      "answer": 1,
      "explain": "Xương đùi là xương ống dài chứa nhiều tủy vàng (mỡ). Chấn thương hoặc thao tác đóng đinh nội tủy làm tăng áp lực, đẩy mỡ vào tĩnh mạch về phổi gây tắc mạch mỡ."
    },
    {
      "q": "Cơ sở sinh lý bệnh nào giải thích việc gãy thân xương đùi ở trẻ em dưới 5 tuổi có khả năng tự sửa chữa di lệch gập góc và chồng ngàm rất tốt?",
      "options": [
        "Do tủy xương trẻ em chưa tạo sụn",
        "Do màng xương rất dày, sức tạo xương mạnh và sụn phát triển hoạt động tích cực",
        "Do khối lượng cơ ở trẻ em rất yếu, không gây co kéo",
        "Do xương trẻ em chủ yếu là chất vô cơ nên dễ uốn nắn"
      ],
      "answer": 1,
      "explain": "Sự tự chỉnh hình (remodeling) ở trẻ em rất mạnh mẽ nhờ màng xương dày và các sụn phát triển còn mở, cho phép bù đắp di lệch ngắn chi và gập góc."
    },
    {
      "q": "Tại sao gãy 1/3 dưới thân xương đùi có nguy cơ cao nhất gây tổn thương động mạch khoeo?",
      "options": [
        "Do động mạch khoeo chạy ngay sát mặt trước xương đùi",
        "Do mạn sườn ngoài đâm trực tiếp vào mạch",
        "Do đầu gãy xa bị cơ sinh đôi kéo gập ra sau chọc vào hố khoeo",
        "Do lực chấn thương luôn là lực trực tiếp từ phía sau"
      ],
      "answer": 2,
      "explain": "Bẫy cơ chế kinh điển: Cơ sinh đôi co rút làm đầu trên của đoạn gãy dưới (đầu nhọn) bẩy ra phía sau, đâm thẳng vào bó mạch thần kinh khoeo nằm ngay sát đó."
    },
    {
      "q": "Trong giờ đầu sau gãy hoàn toàn thân xương đùi, biến chứng toàn thân nào nổi bật và đe dọa tính mạng nhất?",
      "options": [
        "Viêm phổi cấp",
        "Tắc tĩnh mạch sâu chi dưới",
        "Sốc chấn thương",
        "Cứng khớp gối"
      ],
      "answer": 2,
      "explain": "Sốc chấn thương do đau đớn dữ dội và mất máu nhiều (có thể >1.5 lít) là biến chứng cấp tính nguy hiểm nhất cần được phòng chống ngay lập tức."
    },
    {
      "q": "Dấu hiệu nào sau đây là dấu hiệu chắc chắn để chẩn đoán gãy xương đùi trên lâm sàng?",
      "options": [
        "Đau chói và sưng nề nhiều vùng đùi",
        "Bầm tím lan rộng xuống tận khớp gối",
        "Biến dạng gập góc và có lạo xạo xương",
        "Mất cơ năng chi dưới hoàn toàn"
      ],
      "answer": 2,
      "explain": "3 dấu hiệu chắc chắn gãy xương gồm: Biến dạng, cử động bất thường và lạo xạo xương. Đau, sưng, mất cơ năng chỉ là dấu hiệu không chắc chắn."
    },
    {
      "q": "Tư thế biến dạng chi điển hình nhất của gãy hoàn toàn 1/3 giữa thân xương đùi ở người lớn khi nằm ngửa là gì?",
      "options": [
        "Chi ngắn, đùi xoay trong, gập góc mở ra ngoài",
        "Chi ngắn, bàn chân xoay ngoài đổ sát mặt giường, đùi sưng to gập góc",
        "Chi dài ra, bàn chân đổ ngoài, đùi thẳng trục",
        "Chi không thay đổi chiều dài nhưng mất toàn bộ vận động"
      ],
      "answer": 1,
      "explain": "Do co rút cơ, chi luôn bị ngắn lại; do trọng lượng bàn chân và nhóm cơ chậu hông, chi thường xoay ngoài. Đùi rất to và có biến dạng gập góc rõ."
    },
    {
      "q": "Mốc giải phẫu chuẩn để đo chiều dài tuyệt đối của xương đùi trên lâm sàng là từ đâu đến đâu?",
      "options": [
        "Gai chậu trước trên đến khe khớp đùi chày trong",
        "Mấu chuyển lớn đến khe khớp đùi chày ngoài",
        "Rốn đến mắt cá trong",
        "Gai chậu trước trên đến mắt cá trong"
      ],
      "answer": 1,
      "explain": "Chiều dài tuyệt đối đo dọc theo chiều dài thực tế của xương đó, từ điểm đầu (mấu chuyển lớn) đến điểm cuối (khe khớp đùi chày ngoài)."
    },
    {
      "q": "Mục đích ưu tiên số một của thao tác bắt mạch mu chân và mạch chày sau ở bệnh nhân vừa gãy thân xương đùi là gì?",
      "options": [
        "Đánh giá nhịp tim để phân độ sốc",
        "Kiểm tra xem gãy xương có đi kèm tổn thương tắc nghẽn động mạch chi dưới hay không",
        "Tiên lượng khả năng hồi phục chức năng vận động",
        "Phân biệt gãy xương đùi với trật khớp háng"
      ],
      "answer": 1,
      "explain": "Luôn phải khám mạch ngoại vi (mạch mu chân, chày sau) để phát hiện sớm biến chứng chấn thương mạch máu vùng đùi hoặc khoeo."
    },
    {
      "q": "Dấu hiệu lâm sàng nào báo động bệnh nhân gãy thân xương đùi đang diễn tiến biến chứng chèn ép khoang cấp tính?",
      "options": [
        "Đau chói khu trú khi ấn vào ổ gãy",
        "Tê bì nhẹ vùng mặt ngoài đùi",
        "Đau dữ dội liên tục, không đáp ứng thuốc giảm đau, đau tăng khi kéo giãn thụ động các cơ ngón chân",
        "Cảm giác lạo xạo xương xuất hiện rõ rệt mỗi khi thở"
      ],
      "answer": 2,
      "explain": "Dấu hiệu 'đau tăng khi kéo căng cơ thụ động' là dấu hiệu sớm và nhạy nhất của chèn ép khoang, cùng với đùi căng cứng và đau ngoài mức độ chấn thương."
    },
    {
      "q": "Khám vận động gấp, duỗi chủ động các ngón chân ở bệnh nhân gãy thân xương đùi nhằm mục đích cốt lõi gì?",
      "options": [
        "Đánh giá sức mạnh cơ tứ đầu đùi",
        "Sàng lọc tổn thương dây thần kinh hông to hoặc các nhánh của nó",
        "Đánh giá nguy cơ hoại tử cẳng chân",
        "Kiểm tra sự toàn vẹn của khớp cổ chân"
      ],
      "answer": 1,
      "explain": "Thần kinh hông to (thần kinh tọa) chi phối vận động vùng cẳng - bàn chân. Liệt gấp/duỗi ngón chân chứng tỏ có tổn thương thần kinh tọa vùng đùi."
    },
    {
      "q": "Tràn dịch khớp gối xuất hiện nhanh chóng ngay sau khi bệnh nhân bị gãy 1/3 dưới thân xương đùi gợi ý tổn thương nào?",
      "options": [
        "Rách hoàn toàn dây chằng chéo trước",
        "Rách sụn chêm gối kèm theo",
        "Ổ gãy xương đùi thông vào khớp gối hoặc rách bao khớp làm máu chảy vào khớp",
        "Thoái hóa khớp gối bùng phát cấp tính"
      ],
      "answer": 2,
      "explain": "Trong gãy 1/3 dưới, nếu đường gãy phạm khớp hoặc xé rách túi cùng thanh mạc, máu từ ổ gãy sẽ chảy thẳng vào khớp gối gây tràn máu khớp nhanh."
    },
    {
      "q": "Về triệu chứng 'đau chói tại chỗ' trong gãy thân xương đùi, nhận định nào sau đây là chuẩn xác nhất?",
      "options": [
        "Là dấu hiệu chắc chắn để khẳng định gãy xương",
        "Chỉ xuất hiện trong gãy xương hở",
        "Là dấu hiệu không chắc chắn, dùng để hướng tới vị trí ổ gãy",
        "Bắt buộc phải tìm thấy để có chỉ định chụp X-quang"
      ],
      "answer": 2,
      "explain": "Đau chói là triệu chứng chủ quan, có thể do đụng dập phần mềm màng xương. Đây là dấu hiệu hướng điểm, không phải dấu hiệu chắc chắn. Cần thận trọng tránh làm bệnh nhân sốc."
    },
    {
      "q": "Trong quá trình thăm khám lâm sàng bệnh nhân nghi gãy thân xương đùi cấp tính, thao tác nào sau đây KHÔNG ĐƯỢC làm chủ động?",
      "options": [
        "Đo chiều dài chi dưới để tìm dấu hiệu ngắn chi",
        "Cố ý cử động đùi để tìm tiếng lạo xạo xương và cử động bất thường",
        "Bắt mạch ngoại vi hai bên để so sánh",
        "Quan sát biến dạng trục chi"
      ],
      "answer": 1,
      "explain": "Cố ý tìm lạo xạo xương hoặc cử động bất thường gây đau đớn tột cùng, làm tăng sốc, đứt mạch máu thần kinh và tổn thương thêm phần mềm. Tuyệt đối cấm chủ động tìm."
    },
    {
      "q": "Một bệnh nhân gãy 1/3 dưới xương đùi mất vận động vểnh bàn chân lên (rơi bàn chân) và mất cảm giác vùng kẽ ngón 1-2. Thần kinh nào đã bị tổn thương?",
      "options": [
        "Thần kinh đùi",
        "Thần kinh mác nông",
        "Thần kinh chày",
        "Thần kinh mác chung (mác sâu)"
      ],
      "answer": 3,
      "explain": "Tổn thương nhánh mác chung (đặc biệt mác sâu chi phối cơ chày trước và kẽ ngón 1-2) gây rủ bàn chân. Do thần kinh hông to chia nhánh mác chung và chày ở vùng đùi dưới."
    },
    {
      "q": "Điểm khác biệt quan trọng nhất về biến dạng chi trên lâm sàng giúp chẩn đoán phân biệt gãy thân xương đùi và gãy cổ xương đùi là gì?",
      "options": [
        "Gãy cổ xương đùi chi ngắn nhiều hơn thân xương đùi",
        "Gãy thân xương đùi có gập góc rõ ở vùng đùi, trong khi gãy cổ xương đùi thì trục đùi vẫn thẳng",
        "Gãy thân xương đùi chi xoay trong, gãy cổ xương đùi chi xoay ngoài",
        "Cả hai đều có biến dạng sưng nề y hệt nhau, chỉ có thể phân biệt bằng X-quang"
      ],
      "answer": 1,
      "explain": "Gãy cổ xương đùi nằm sâu trong khớp háng nên không gây gập góc ở giữa đùi, chi xoay ngoài sát mặt giường. Gãy thân xương đùi gây biến dạng, gập góc trục đùi rất rõ ràng."
    },
    {
      "q": "Tiêu chuẩn kỹ thuật tối thiểu khi chụp X-quang chẩn đoán gãy thân xương đùi là gì?",
      "options": [
        "Chụp thẳng và nghiêng, lấy được trung tâm ổ gãy",
        "Chụp thẳng và nghiêng, lấy được toàn bộ thân xương và hai khớp lân cận (háng, gối)",
        "Chỉ cần chụp bình diện thẳng lấy toàn bộ xương đùi",
        "Chụp thẳng, nghiêng và chụp cắt lớp vi tính thường quy"
      ],
      "answer": 1,
      "explain": "Nguyên tắc kinh điển của X-quang xương dài là phải chụp 2 bình diện vuông góc (thẳng, nghiêng) và lấy qua 2 khớp trên và dưới ổ gãy để tránh bỏ sót tổn thương."
    },
    {
      "q": "Theo phân loại Winquist-Hansen dùng cho gãy thân xương đùi, độ II được định nghĩa như thế nào?",
      "options": [
        "Gãy ngang không có mảnh rời",
        "Có mảnh rời, mảnh rời chiếm dưới 50% chu vi thân xương",
        "Mảnh rời lớn chiếm trên 50% chu vi thân xương",
        "Gãy nát nhiều mảnh, mất hoàn toàn sự tiếp xúc của hai đầu xương chính"
      ],
      "answer": 1,
      "explain": "Phân loại Winquist dựa trên mức độ nát vỏ xương: Độ I (mảnh nhỏ), Độ II (<50%), Độ III (>50%), Độ IV (gãy nát chu vi 100%, mất tiếp xúc trục)."
    },
    {
      "q": "Xét nghiệm cận lâm sàng nào cần được ưu tiên chỉ định và làm lại nhiều lần để theo dõi biến chứng sốc ở bệnh nhân gãy thân xương đùi những giờ đầu?",
      "options": [
        "Chức năng gan (AST, ALT)",
        "Ion đồ (Na+, K+)",
        "Huyết đồ (Hemoglobin và Hematocrit)",
        "X-quang phổi tại giường"
      ],
      "answer": 2,
      "explain": "Theo dõi Hb và Hct giúp đánh giá tình trạng mất máu liên tục vào khoang đùi, từ đó có chỉ định truyền máu kịp thời và kiểm soát sốc giảm thể tích."
    },
    {
      "q": "Hình ảnh X-quang thấy một ổ khuyết xương ở thân xương đùi, vỏ xương mỏng mòn, đường gãy ngang tại vị trí này ở bệnh nhân chỉ bị trượt ngã nhẹ gợi ý chẩn đoán gì?",
      "options": [
        "Gãy xương do mỏi (stress fracture)",
        "Gãy xương trên nền xương bệnh lý (nang xương, u xương)",
        "Gãy xương chéo xoắn do cơ chế vặn",
        "Gãy xương bong điểm bám"
      ],
      "answer": 1,
      "explain": "Lực chấn thương nhẹ (chấn thương sinh hoạt) nhưng gây gãy xương đùi tại vị trí có khuyết/mỏng vỏ xương trên X-quang là dấu hiệu điển hình của gãy xương bệnh lý."
    },
    {
      "q": "Việc chỉ định chụp Cắt lớp vi tính (CT scan) có ý nghĩa và cần thiết nhất trong trường hợp nào sau đây ở bệnh nhân gãy thân xương đùi?",
      "options": [
        "Để xác định lượng máu tụ phần mềm vùng đùi",
        "Để theo dõi quá trình tạo can xương sau 2 tuần",
        "Nghi ngờ có kèm theo gãy cổ xương đùi hoặc gãy phạm khớp gối mà X-quang thường quy không rõ",
        "Để phân độ Winquist-Hansen chính xác hơn"
      ],
      "answer": 2,
      "explain": "Khoảng 1-9% gãy thân xương đùi có kèm gãy cổ xương đùi đồng thời. Chụp CT giúp chẩn đoán xác định các tổn thương ẩn ở cổ xương đùi hoặc khớp gối mà X-quang che lấp."
    },
    {
      "q": "Sự thay đổi nào trên xét nghiệm Khí máu động mạch (ABG) là dấu hiệu cảnh báo sớm nhất của hội chứng tắc mạch mỡ ở bệnh nhân gãy xương đùi?",
      "options": [
        "PaCO2 tăng cao trên 50 mmHg",
        "PaO2 giảm thấp dưới 60 mmHg",
        "pH máu tăng trên 7.45 (kiềm hô hấp)",
        "HCO3- giảm sâu"
      ],
      "answer": 1,
      "explain": "Tình trạng thiếu oxy máu (Hypoxemia) với PaO2 < 60 mmHg là tiêu chuẩn sinh hóa sớm và nhạy của hội chứng tắc mạch mỡ trước khi các triệu chứng thần kinh hay da xuất hiện."
    },
    {
      "q": "Siêu âm Doppler mạch máu chi dưới nên được ưu tiên chỉ định khẩn cấp cho bệnh nhân gãy thân xương đùi khi có biểu hiện nào?",
      "options": [
        "Đùi sưng to căng bóng và bầm tím lan rộng",
        "Rối loạn cảm giác vùng kẽ ngón chân 1-2",
        "Chỉ số huyết áp tại cổ chân so với cánh tay (ABI) < 0.9 hoặc chi lạnh, mất mạch mu chân",
        "Bệnh nhân có tiền sử tăng huyết áp và xơ vữa mạch"
      ],
      "answer": 2,
      "explain": "Mất mạch ngoại vi, chi lạnh tủy, hoặc chỉ số ABI giảm < 0.9 là dấu hiệu thiếu máu chi cấp, cần siêu âm Doppler hoặc chụp mạch ngay để xác định vị trí tắc/đứt mạch máu."
    },
    {
      "q": "Trong quy trình chuẩn bị mổ kết hợp xương đùi cho người lớn khỏe mạnh cấp cứu, xét nghiệm nào KHÔNG bắt buộc thực hiện thường quy?",
      "options": [
        "Nhóm máu và phản ứng chéo",
        "Đông máu cơ bản (PT, aPTT)",
        "Xét nghiệm Marker dấu ấn ung thư xương (ALP, LDH)",
        "Tổng phân tích tế bào máu ngoại vi"
      ],
      "answer": 2,
      "explain": "Marker ung thư chỉ làm khi nghi ngờ gãy xương bệnh lý do u trên X-quang. Nhóm máu, đông máu và công thức máu là bắt buộc do nguy cơ chảy máu cao."
    },
    {
      "q": "Tại sao X-quang đùi chụp tại giường cho bệnh nhân đa chấn thương rất dễ bỏ sót di lệch gập góc ổ gãy?",
      "options": [
        "Do máy X-quang tại giường không đủ công suất tia X",
        "Do tư thế nằm ngửa thường làm xương tự nắn chỉnh tốt",
        "Do thường chỉ chụp được bình diện thẳng (AP) mà thiếu bình diện nghiêng",
        "Do bệnh nhân đa chấn thương thường có dịch màng phổi che lấp"
      ],
      "answer": 2,
      "explain": "Bệnh nhân đa chấn thương khó nghiêng người, chụp tại giường thường chỉ lấy phim AP (trước-sau). Gập góc trước-sau chỉ thấy rõ trên phim nghiêng nên rất dễ bỏ sót."
    },
    {
      "q": "Hệ thống phân loại gãy xương của AO/OTA (Arbeitsgemeinschaft für Osteosynthesefragen) quy định mã số nào để chỉ định vùng thân xương đùi?",
      "options": [
        "12",
        "22",
        "32",
        "42"
      ],
      "answer": 2,
      "explain": "Theo chuẩn AO, số 3 là xương đùi, vùng số 1 là đầu trên, số 2 là thân xương, số 3 là đầu dưới. Do đó, 32 là gãy thân xương đùi."
    },
    {
      "q": "Nguyên tắc sống còn trong sơ cứu bất động gãy xương đùi tại hiện trường là gì?",
      "options": [
        "Chỉ cần tiêm morphin giảm đau, không cần nẹp",
        "Cố định bằng 3 nẹp gỗ cứng từ nách/mào chậu đến quá gót chân, đảm bảo bất động qua 2 khớp háng và gối",
        "Kéo nắn lập tức đưa xương về trục thẳng rồi bó bột",
        "Cố định bằng nẹp ngắn từ nếp bẹn đến nếp khoeo"
      ],
      "answer": 1,
      "explain": "Xương đùi lớn, cơ kéo mạnh. Bất động phải đủ dài qua 2 khớp lân cận (háng và gối) bằng nẹp Thomas hoặc nẹp gỗ mộc để chống sốc và chống di lệch thứ phát."
    },
    {
      "q": "'Tiêu chuẩn vàng' (phẫu thuật lựa chọn số 1) trong điều trị gãy kín 1/3 giữa thân xương đùi ở người trưởng thành hiện nay là phương pháp nào?",
      "options": [
        "Kết hợp xương bằng nẹp vít nén ép",
        "Đóng đinh nội tủy có chốt ngang",
        "Xuyên đinh cố định ngoài",
        "Kéo liên tục trên khung Braun đến khi liền xương"
      ],
      "answer": 1,
      "explain": "Đóng đinh nội tủy có chốt kiểm soát tốt sự di lệch, chịu lực tốt theo trục sinh lý, sẹo mổ nhỏ, ít tàn phá màng xương và cho phép tỳ đè sớm."
    },
    {
      "q": "Chống chỉ định tuyệt đối của phẫu thuật đóng đinh nội tủy thân xương đùi là gì?",
      "options": [
        "Bệnh nhân có chấn thương ngực kín kèm theo",
        "Gãy nát phức tạp thành nhiều mảnh",
        "Tình trạng nhiễm khuẩn tại chỗ vùng mổ đang tiến triển",
        "Bệnh nhân lớn tuổi bị loãng xương"
      ],
      "answer": 2,
      "explain": "Nhiễm trùng tại chỗ là chống chỉ định tuyệt đối cho các dụng cụ kết hợp xương bên trong (đinh, nẹp). Phải dùng cố định ngoài hoặc kéo liên tục."
    },
    {
      "q": "Chỉ định ưu tiên nhất của khung cố định ngoài trong điều trị gãy thân xương đùi là trường hợp nào?",
      "options": [
        "Gãy chéo xoắn đơn giản ở người trẻ",
        "Gãy xương hở độ I đến trước 6 giờ",
        "Bệnh nhân đa chấn thương có huyết động không ổn định cần kiểm soát thiệt hại",
        "Gãy xương bệnh lý do nang xương"
      ],
      "answer": 2,
      "explain": "Cố định ngoài được dùng trong phương pháp 'Kiểm soát thiệt hại chỉnh hình' (Damage Control Orthopedics) giúp bất động nhanh chóng, ít mất máu, để cứu sống bệnh nhân trước."
    },
    {
      "q": "Cơ chế cơ sinh học nào giúp đinh nội tủy có ưu điểm liền xương vượt trội hơn nẹp vít trong điều trị gãy thân xương đùi?",
      "options": [
        "Chia sẻ tải trọng do nằm ở trung tâm trục cơ học của xương, tạo vi vận động kích thích can xương",
        "Chịu toàn bộ tải trọng giúp xương hoàn toàn không bị áp lực",
        "Nén ép các mảnh gãy chặt khít tuyệt đối như nẹp vít",
        "Phá hủy tủy xương tạo ra tế bào gốc kích thích liền xương"
      ],
      "answer": 0,
      "explain": "Đinh nội tủy là thiết bị load-sharing (chia sẻ lực tải), nằm đúng trục dọc, cho phép truyền lực ép vi thể lên ổ gãy khi tỳ đè, giúp xương mau liền hơn thiết bị nén ép cứng nhắc."
    },
    {
      "q": "Tại sao kết hợp xương bằng nẹp vít lại ít được ưu tiên sử dụng cho gãy 1/3 giữa thân xương đùi ở người lớn?",
      "options": [
        "Do không có loại nẹp nào đủ dài cho xương đùi",
        "Do nẹp vít dễ bị tuột ốc do xương đùi quá cứng",
        "Do nẹp chịu lực uốn bẻ rất lớn, nguy cơ gãy nẹp cao, đồng thời mổ mở làm tàn phá màng xương nhiều",
        "Do đắt tiền hơn đinh nội tủy rất nhiều"
      ],
      "answer": 2,
      "explain": "Trục xương đùi chịu tải trọng lớn dạng bẻ cong. Nẹp đặt lệch trục trung tâm nên phải chịu lực uốn này, dễ gãy. Đồng thời mổ nẹp bóc tách cơ nhiều làm hỏng nguồn nuôi màng xương."
    },
    {
      "q": "Mục đích chính của kỹ thuật xuyên đinh kéo liên tục trước mổ ở bệnh nhân gãy thân xương đùi người lớn là gì?",
      "options": [
        "Để xương tự liền chắc chắn mà không cần phẫu thuật",
        "Để giảm đau, chống co rút cơ, duy trì trục chi tạm thời chờ tình trạng toàn thân ổn định để phẫu thuật",
        "Để nong rộng ống tủy trước khi đóng đinh",
        "Để điều trị dự phòng biến chứng tắc mạch mỡ"
      ],
      "answer": 1,
      "explain": "Khi bệnh nhân chưa đủ điều kiện mổ cấp cứu (sốc, đa chấn thương), kéo liên tục qua lồi củ chày giúp chống co kéo cơ, giữ thẳng trục, tránh xương chọc thêm vào phần mềm."
    },
    {
      "q": "Vị trí giải phẫu nào thường được lựa chọn chuẩn mực để xuyên đinh Steinmann kéo liên tục trong gãy thân xương đùi?",
      "options": [
        "Xuyên qua cổ xương đùi",
        "Xuyên qua lồi củ trước xương chày hoặc lồi cầu đùi",
        "Xuyên qua mấu chuyển lớn xương đùi",
        "Xuyên qua hai mắt cá chân"
      ],
      "answer": 1,
      "explain": "Lồi củ xương chày (cách mặt khớp 2cm, cách mào chày 2cm ra ngoài) là vị trí an toàn, chịu lực kéo tốt nhất và tránh phạm khớp. Đôi khi xuyên qua lồi cầu đùi nhưng dễ gây cứng khớp gối."
    },
    {
      "q": "Ở trẻ em dưới 3 tuổi bị gãy thân xương đùi, phương pháp điều trị nào sau đây thường được ưu tiên lựa chọn nhất?",
      "options": [
        "Đóng đinh nội tủy có chốt luồn qua mấu chuyển lớn",
        "Nẹp vít nén ép tuyệt đối",
        "Kéo liên tục kéo bổng hai chân thẳng lên trời (kiểu Bryant) hoặc bó bột ếch",
        "Bó bột ống ngay lập tức không nắn chỉnh"
      ],
      "answer": 2,
      "explain": "Với trẻ nhỏ < 3 tuổi, trọng lượng nhẹ, kéo Bryant hoặc bó bột chậu-lưng-chân (bột ếch) là tiêu chuẩn vàng vì xương trẻ lành rất nhanh, tự nắn chỉnh cực tốt, tránh can thiệp vào sụn tiếp hợp."
    },
    {
      "q": "Trong kỹ thuật mổ đóng đinh nội tủy có chốt, việc bắt các ốc chốt ngang qua đinh nhằm mục đích cơ sinh học nào?",
      "options": [
        "Tăng cường khả năng chịu lực nén dọc của đinh",
        "Chống sự xoay vặn và chống di lệch chồng ngàm (ngắn chi) cho hai đoạn gãy",
        "Kích thích tủy xương tạo máu",
        "Ép hai mặt gãy lại gần nhau tuyệt đối"
      ],
      "answer": 1,
      "explain": "Đinh nội tủy không chốt dễ làm ổ gãy xoay quanh trục đinh hoặc tụt chồng ngàm gây ngắn chi. Chốt ngang tĩnh (static locking) khóa chặt 2 đầu xương vào đinh ngăn chặn các lực này."
    },
    {
      "q": "Biến chứng cấp tính nào là nguyên nhân hàng đầu gây tử vong sớm ở bệnh nhân gãy thân xương đùi kín, đơn thuần nếu không được sơ cấp cứu đúng cách?",
      "options": [
        "Nhiễm khuẩn huyết từ ổ gãy",
        "Sốc do mất máu và đau đớn dữ dội",
        "Nhồi máu cơ tim cấp",
        "Viêm phổi do hít sặc"
      ],
      "answer": 1,
      "explain": "Gãy xương đùi mất rất nhiều máu và đau đớn khủng khiếp. Sốc giảm thể tích kết hợp sốc thần kinh có thể gây tử vong ngay tại hiện trường hoặc trên đường vận chuyển."
    },
    {
      "q": "Tam chứng kinh điển của Hội chứng tắc mạch mỡ (xuất hiện sau gãy xương đùi khoảng 24 - 72 giờ) bao gồm những triệu chứng gì?",
      "options": [
        "Suy hô hấp, rối loạn tri giác, ban xuất huyết dưới da ở ngực/nách",
        "Suy tim cấp, suy thận vô niệu, tiểu ra mỡ",
        "Đau ngực dữ dội, ho ra máu ồ ạt, liệt nửa người",
        "Sốt cao liên tục, rét run, vàng da niêm mạc"
      ],
      "answer": 0,
      "explain": "Đây là tam chứng lâm sàng đặc trưng của Gurd dùng để chẩn đoán tắc mạch mỡ. Tỉ lệ tử vong cao do tổn thương phổi (ARDS) và phù não."
    },
    {
      "q": "Đặc điểm hình ảnh X-quang điển hình nhất của biến chứng khớp giả (Non-union) sau gãy xương đùi được đánh giá sau 6 tháng là gì?",
      "options": [
        "Có rất nhiều can xương xù xì bao bọc xung quanh ổ gãy",
        "Đầu xương xốp, nham nhở, có nhiều phản ứng tạo màng xương mới",
        "Khe gãy vẫn còn, ống tủy bị bít kín, hai đầu xương xơ đặc (sclerosis) và tròn nhẵn",
        "Ống tủy rộng ra, khe gãy mờ dần nhưng xương bị cong vẹo"
      ],
      "answer": 2,
      "explain": "Khớp giả là sự ngưng hoàn toàn quá trình liền xương. Hình ảnh X-quang cho thấy hai đầu xương xơ cứng (đặc xương), bít ống tủy, tạo thành hình ảnh như mỏ chim, vĩnh viễn không liền nếu không mổ lại."
    },
    {
      "q": "Trong theo dõi chèn ép khoang đùi do gãy xương, tiêu chuẩn áp lực khoang tuyệt đối nào chỉ định bắt buộc phải rạch cân giải áp khẩn cấp?",
      "options": [
        "Áp lực khoang > 10 mmHg",
        "Áp lực khoang > 15 mmHg",
        "Áp lực khoang > 30 mmHg (hoặc Delta P < 30 mmHg)",
        "Áp lực khoang bằng với huyết áp tâm thu"
      ],
      "answer": 2,
      "explain": "Khi áp lực trong khoang đùi vượt quá 30 mmHg (hoặc Delta P = Huyết áp tâm trương - Áp lực khoang < 30 mmHg), tuần hoàn mao mạch bị ngưng trệ hoàn toàn gây hoại tử cơ, bắt buộc rạch cân."
    }
  ]
}